setup.py
Coins.egg-info/PKG-INFO
Coins.egg-info/SOURCES.txt
Coins.egg-info/dependency_links.txt
Coins.egg-info/not-zip-safe
Coins.egg-info/requires.txt
Coins.egg-info/top_level.txt
coins/__init__.py
coins/b58check.py
coins/entropy.py
coins/keypair.py
coins/keyspace.py
coins/passphrase.py
coins/utils.py
coins/words.py
coins.egg-info/SOURCES.txt