Metadata-Version: 1.1
Name: Coins
Version: 0.2.2
Summary: Tools for Bitcoin & other cryptocurrencies (incl. Litecoin, Namecoin, Peercoin, Primecoin, Dogecoin, Worldcoin, Megacoin, Anoncoin, Feathercoin, Terracoin, and Novacoin).
Home-page: https://github.com/halfmoonlabs/coins
Author: Halfmoon Labs
Author-email: hello@halfmoon.io
License: MIT
Keywords: bitcoin btc litecoin namecoin peercoin primecoin cryptocurrency
Platform: UNKNOWN
Classifier: Intended Audience :: Developers
Classifier: License :: OSI Approved :: MIT License
Classifier: Operating System :: OS Independent
Classifier: Programming Language :: Python
Classifier: Topic :: Internet
Classifier: Topic :: Security :: Cryptography
Classifier: Topic :: Software Development :: Libraries :: Python Modules
